{"Summary":{"Sales":{"StatsModel":{"Sales":{"TotalSales":28.0,"SpentOnSnacks":0.0,"SpentOnOffers":28.0,"SpentOnPackageDeals":0.0,"GuestSpentOnSnacks":0.0,"GuestSpentOnOffers":0.0,"GuestSpentOnPackageDeals":0.0,"PaidWithBalance":0.0,"SpentOnBookings":0.0},"Income":{"TotalIncome":28.0,"CashIncome":15.0,"CardIncome":13.0,"CashSales":15.0,"CardSales":13.0,"CashDeposits":0.0,"CardDeposits":0.0},"PrizesBought":0,"RefundsCount":0,"TotalRefunds":0.0,"Taxes":null,"NextResetTime":"0001-01-01T00:00:00"},"Chart":{"2022-02-14T23:00:00Z":{"Offers":0.0,"Products":0.0,"UserDeposits":0.0},"2022-02-14T22:30:00Z":{"Offers":0.0,"Products":0.0,"UserDeposits":0.0},"2022-02-14T22:00:00Z":{"Offers":0.0,"Products":0.0,"UserDeposits":0.0},"2022-02-14T21:30:00Z":{"Offers":0.0,"Products":0.0,"UserDeposits":0.0},"2022-02-14T21:00:00Z":{"Offers":0.0,"Products":0.0,"UserDeposits":0.0},"2022-02-14T20:30:00Z":{"Offers":0.0,"Products":0.0,"UserDeposits":0.0},"2022-02-14T20:00:00Z":{"Offers":0.0,"Products":0.0,"UserDeposits":0.0},"2022-02-14T19:30:00Z":{"Offers":0.0,"Products":0.0,"UserDeposits":0.0},"2022-02-14T19:00:00Z":{"Offers":0.0,"Products":0.0,"UserDeposits":0.0},"2022-02-14T18:30:00Z":{"Offers":15.0,"Products":0.0,"UserDeposits":0.0},"2022-02-14T16:30:00Z":{"Offers":0.0,"Products":0.0,"UserDeposits":0.0},"2022-02-14T14:30:00Z":{"Offers":0.0,"Products":0.0,"UserDeposits":0.0},"2022-02-14T14:00:00Z":{"Offers":13.0,"Products":0.0,"UserDeposits":0.0},"2022-02-14T13:30:00Z":{"Offers":0.0,"Products":0.0,"UserDeposits":0.0},"2022-02-14T13:00:00Z":{"Offers":0.0,"Products":0.0,"UserDeposits":0.0},"2022-02-14T12:30:00Z":{"Offers":0.0,"Products":0.0,"UserDeposits":0.0},"2022-02-14T12:00:00Z":{"Offers":0.0,"Products":0.0,"UserDeposits":0.0},"2022-02-14T11:30:00Z":{"Offers":0.0,"Products":0.0,"UserDeposits":0.0},"2022-02-14T11:00:00Z":{"Offers":0.0,"Products":0.0,"UserDeposits":0.0},"2022-02-14T10:30:00Z":{"Offers":0.0,"Products":0.0,"UserDeposits":0.0},"2022-02-14T10:00:00Z":{"Offers":0.0,"Products":0.0,"UserDeposits":0.0},"2022-02-14T15:00:00Z":{"Offers":0.0,"Products":0.0,"UserDeposits":0.0},"2022-02-14T15:30:00Z":{"Offers":0.0,"Products":0.0,"UserDeposits":0.0},"2022-02-14T16:00:00Z":{"Offers":0.0,"Products":0.0,"UserDeposits":0.0},"2022-02-14T17:00:00Z":{"Offers":0.0,"Products":0.0,"UserDeposits":0.0},"2022-02-14T17:30:00Z":{"Offers":0.0,"Products":0.0,"UserDeposits":0.0},"2022-02-14T18:00:00Z":{"Offers":0.0,"Products":0.0,"UserDeposits":0.0},"2022-02-14T23:30:00Z":{"Offers":0.0,"Products":0.0,"UserDeposits":0.0}},"ChartInterval":"00:30:00","ByProductCategory":{"619165d6-8b6b-49e0-948b-8819c2bcda7f":[{"Uuid":"e6e9272c-532d-4d92-bf09-e1cf4837fb1b","Name":"4 Hours ","Price":15.0,"QuantitySold":1.0,"QuantityRefunded":0.0,"Offer":{"CenterUuid":"7a4a5db0-2e79-41c0-a02d-5e82facd83c2","OfferUuid":"b45b3955-eba9-40b4-bdfe-7f6e259a6d4f","UserOfferUuids":[],"Name":"4 Hours ","Price":15.0,"Seconds":14400,"Type":"StartOnFirstUse","Priority":"Normal","HasFixedStart":false,"FixedStartTime":"00:00","ExpiresAfterDays":false,"ExpiryDays":0,"ExpiresAtFixedTime":false,"ExpiryFixedTime":"00:00","EligibleDays":[0,1,2,3,4,5,6],"EligibleTimeStart":"00:00","EligibleTimeEnd":"00:00","CoinsBonus":0.0},"NetValue":15.0,"CostPrice":0.0,"Tax":{"Id":"1","Name":"Tax 1","Percentage":0.0,"Square":null},"PurchasedAt":"2022-02-14T18:30:36.355Z","Employee":"bepis","User":"ndroumev","ManualTimeSeconds":0,"TotalDiscount":0.0,"Total":15.0},{"Uuid":"42934ef0-e11e-4fa2-876a-73ba6564b6db","Name":"2 Hours","Price":8.0,"QuantitySold":1.0,"QuantityRefunded":0.0,"Offer":{"CenterUuid":"7a4a5db0-2e79-41c0-a02d-5e82facd83c2","OfferUuid":"9a622783-2a4e-44f8-9ab9-b96d48828878","UserOfferUuids":[],"Name":"2 Hours","Price":8.0,"Seconds":7200,"Type":"StartOnFirstUse","Priority":"Normal","HasFixedStart":false,"FixedStartTime":"00:00","ExpiresAfterDays":false,"ExpiryDays":0,"ExpiresAtFixedTime":false,"ExpiryFixedTime":"00:00","EligibleDays":[0,1,2,3,4,5,6],"EligibleTimeStart":"00:00","EligibleTimeEnd":"00:00","CoinsBonus":0.0},"NetValue":8.0,"CostPrice":0.0,"Tax":{"Id":"1","Name":"Tax 1","Percentage":0.0,"Square":null},"PurchasedAt":"2022-02-14T14:27:30.498Z","Employee":"uowarwick","User":"levs1","ManualTimeSeconds":0,"TotalDiscount":0.0,"Total":8.0},{"Uuid":"b4760e58-e23c-4d14-aaa5-78a727cae4a7","Name":"1 Hour","Price":5.0,"QuantitySold":1.0,"QuantityRefunded":0.0,"Offer":{"CenterUuid":"7a4a5db0-2e79-41c0-a02d-5e82facd83c2","OfferUuid":"bd379a5b-19b6-480b-8f48-ef28d4226b9e","UserOfferUuids":[],"Name":"1 Hour","Price":5.0,"Seconds":3600,"Type":"StartOnFirstUse","Priority":"Normal","HasFixedStart":false,"FixedStartTime":"00:00","ExpiresAfterDays":false,"ExpiryDays":0,"ExpiresAtFixedTime":false,"ExpiryFixedTime":"00:00","EligibleDays":[0,1,2,3,4,5,6],"EligibleTimeStart":"00:00","EligibleTimeEnd":"00:00","CoinsBonus":0.0},"NetValue":5.0,"CostPrice":0.0,"Tax":{"Id":"1","Name":"Tax 1","Percentage":0.0,"Square":null},"PurchasedAt":"2022-02-14T14:00:17.752Z","Employee":"uowarwick","User":"suetrev","ManualTimeSeconds":0,"TotalDiscount":0.0,"Total":5.0}]},"CategoriesInfo":{"619165d6-8b6b-49e0-948b-8819c2bcda7f":{"Name":"Offers","IsPrize":false}}},"Users":{"ActiveUsers":5,"NewUsers":2,"TotalUsers":1196,"Chart":{"2022-02-14T14:00:00Z":{"New":2,"Active":2},"2022-02-14T23:00:00Z":{"New":0,"Active":1},"2022-02-14T22:30:00Z":{"New":0,"Active":1},"2022-02-14T21:30:00Z":{"New":0,"Active":1},"2022-02-14T21:00:00Z":{"New":0,"Active":1},"2022-02-14T20:30:00Z":{"New":0,"Active":2},"2022-02-14T20:00:00Z":{"New":0,"Active":1},"2022-02-14T19:30:00Z":{"New":0,"Active":1},"2022-02-14T19:00:00Z":{"New":0,"Active":1},"2022-02-14T18:30:00Z":{"New":0,"Active":1},"2022-02-14T16:30:00Z":{"New":0,"Active":1},"2022-02-14T14:30:00Z":{"New":0,"Active":1},"2022-02-14T13:30:00Z":{"New":0,"Active":0},"2022-02-14T13:00:00Z":{"New":0,"Active":0},"2022-02-14T12:30:00Z":{"New":0,"Active":0},"2022-02-14T12:00:00Z":{"New":0,"Active":0},"2022-02-14T11:30:00Z":{"New":0,"Active":0},"2022-02-14T11:00:00Z":{"New":0,"Active":0},"2022-02-14T10:30:00Z":{"New":0,"Active":0},"2022-02-14T10:00:00Z":{"New":0,"Active":0},"2022-02-14T15:00:00Z":{"New":0,"Active":0},"2022-02-14T15:30:00Z":{"New":0,"Active":0},"2022-02-14T16:00:00Z":{"New":0,"Active":0},"2022-02-14T17:00:00Z":{"New":0,"Active":0},"2022-02-14T17:30:00Z":{"New":0,"Active":0},"2022-02-14T18:00:00Z":{"New":0,"Active":0},"2022-02-14T22:00:00Z":{"New":0,"Active":0},"2022-02-14T23:30:00Z":{"New":0,"Active":0}},"ChartInterval":"00:30:00"},"Employees":[{"Name":"uowarwick","EmployeeUuid":"1bafbd92-a05e-47a1-95f3-e9c70a945c59","StatsModel":{"Sales":{"TotalSales":13.0,"SpentOnSnacks":0.0,"SpentOnOffers":13.0,"SpentOnPackageDeals":0.0,"GuestSpentOnSnacks":0.0,"GuestSpentOnOffers":0.0,"GuestSpentOnPackageDeals":0.0,"PaidWithBalance":0.0,"SpentOnBookings":0.0},"Income":{"TotalIncome":13.0,"CashIncome":0.0,"CardIncome":13.0,"CashSales":0.0,"CardSales":13.0,"CashDeposits":0.0,"CardDeposits":0.0},"PrizesBought":0,"RefundsCount":0,"TotalRefunds":0.0,"Taxes":null,"NextResetTime":"0001-01-01T00:00:00"},"AdminModeCount":0,"ShiftsList":[]},{"Name":"Cain","EmployeeUuid":"2bbc1d66-2301-48f0-93be-629aafb29925","StatsModel":{"Sales":{"TotalSales":0.0,"SpentOnSnacks":0.0,"SpentOnOffers":0.0,"SpentOnPackageDeals":0.0,"GuestSpentOnSnacks":0.0,"GuestSpentOnOffers":0.0,"GuestSpentOnPackageDeals":0.0,"PaidWithBalance":0.0,"SpentOnBookings":0.0},"Income":{"TotalIncome":0.0,"CashIncome":0.0,"CardIncome":0.0,"CashSales":0.0,"CardSales":0.0,"CashDeposits":0.0,"CardDeposits":0.0},"PrizesBought":0,"RefundsCount":0,"TotalRefunds":0.0,"Taxes":null,"NextResetTime":"0001-01-01T00:00:00"},"AdminModeCount":0,"ShiftsList":[]},{"Name":"geomancy","EmployeeUuid":"31cfbc3a-8cf4-4a0b-ad83-963a4d7b8a9b","StatsModel":{"Sales":{"TotalSales":0.0,"SpentOnSnacks":0.0,"SpentOnOffers":0.0,"SpentOnPackageDeals":0.0,"GuestSpentOnSnacks":0.0,"GuestSpentOnOffers":0.0,"GuestSpentOnPackageDeals":0.0,"PaidWithBalance":0.0,"SpentOnBookings":0.0},"Income":{"TotalIncome":0.0,"CashIncome":0.0,"CardIncome":0.0,"CashSales":0.0,"CardSales":0.0,"CashDeposits":0.0,"CardDeposits":0.0},"PrizesBought":0,"RefundsCount":0,"TotalRefunds":0.0,"Taxes":null,"NextResetTime":"0001-01-01T00:00:00"},"AdminModeCount":0,"ShiftsList":[]},{"Name":"ndroumev","EmployeeUuid":"6477d15c-d96c-4939-a061-dcf3d978011b","StatsModel":{"Sales":{"TotalSales":0.0,"SpentOnSnacks":0.0,"SpentOnOffers":0.0,"SpentOnPackageDeals":0.0,"GuestSpentOnSnacks":0.0,"GuestSpentOnOffers":0.0,"GuestSpentOnPackageDeals":0.0,"PaidWithBalance":0.0,"SpentOnBookings":0.0},"Income":{"TotalIncome":0.0,"CashIncome":0.0,"CardIncome":0.0,"CashSales":0.0,"CardSales":0.0,"CashDeposits":0.0,"CardDeposits":0.0},"PrizesBought":0,"RefundsCount":0,"TotalRefunds":0.0,"Taxes":null,"NextResetTime":"0001-01-01T00:00:00"},"AdminModeCount":0,"ShiftsList":[]},{"Name":"bhabbichuss","EmployeeUuid":"91001e9f-d829-4312-9171-4e8bf0017436","StatsModel":{"Sales":{"TotalSales":0.0,"SpentOnSnacks":0.0,"SpentOnOffers":0.0,"SpentOnPackageDeals":0.0,"GuestSpentOnSnacks":0.0,"GuestSpentOnOffers":0.0,"GuestSpentOnPackageDeals":0.0,"PaidWithBalance":0.0,"SpentOnBookings":0.0},"Income":{"TotalIncome":0.0,"CashIncome":0.0,"CardIncome":0.0,"CashSales":0.0,"CardSales":0.0,"CashDeposits":0.0,"CardDeposits":0.0},"PrizesBought":0,"RefundsCount":0,"TotalRefunds":0.0,"Taxes":null,"NextResetTime":"0001-01-01T00:00:00"},"AdminModeCount":0,"ShiftsList":[]},{"Name":"Beank","EmployeeUuid":"ad56766e-5dca-4e58-badc-d8339f942b5f","StatsModel":{"Sales":{"TotalSales":0.0,"SpentOnSnacks":0.0,"SpentOnOffers":0.0,"SpentOnPackageDeals":0.0,"GuestSpentOnSnacks":0.0,"GuestSpentOnOffers":0.0,"GuestSpentOnPackageDeals":0.0,"PaidWithBalance":0.0,"SpentOnBookings":0.0},"Income":{"TotalIncome":0.0,"CashIncome":0.0,"CardIncome":0.0,"CashSales":0.0,"CardSales":0.0,"CashDeposits":0.0,"CardDeposits":0.0},"PrizesBought":0,"RefundsCount":0,"TotalRefunds":0.0,"Taxes":null,"NextResetTime":"0001-01-01T00:00:00"},"AdminModeCount":0,"ShiftsList":[]},{"Name":"MageofJustice","EmployeeUuid":"b0db62ae-85a8-406d-a4b6-cce9d0fa4cda","StatsModel":{"Sales":{"TotalSales":0.0,"SpentOnSnacks":0.0,"SpentOnOffers":0.0,"SpentOnPackageDeals":0.0,"GuestSpentOnSnacks":0.0,"GuestSpentOnOffers":0.0,"GuestSpentOnPackageDeals":0.0,"PaidWithBalance":0.0,"SpentOnBookings":0.0},"Income":{"TotalIncome":0.0,"CashIncome":0.0,"CardIncome":0.0,"CashSales":0.0,"CardSales":0.0,"CashDeposits":0.0,"CardDeposits":0.0},"PrizesBought":0,"RefundsCount":0,"TotalRefunds":0.0,"Taxes":null,"NextResetTime":"0001-01-01T00:00:00"},"AdminModeCount":0,"ShiftsList":[]},{"Name":"Kat","EmployeeUuid":"b1a54b4e-0324-4ad2-aeeb-078518f9c367","StatsModel":{"Sales":{"TotalSales":0.0,"SpentOnSnacks":0.0,"SpentOnOffers":0.0,"SpentOnPackageDeals":0.0,"GuestSpentOnSnacks":0.0,"GuestSpentOnOffers":0.0,"GuestSpentOnPackageDeals":0.0,"PaidWithBalance":0.0,"SpentOnBookings":0.0},"Income":{"TotalIncome":0.0,"CashIncome":0.0,"CardIncome":0.0,"CashSales":0.0,"CardSales":0.0,"CashDeposits":0.0,"CardDeposits":0.0},"PrizesBought":0,"RefundsCount":0,"TotalRefunds":0.0,"Taxes":null,"NextResetTime":"0001-01-01T00:00:00"},"AdminModeCount":0,"ShiftsList":[]},{"Name":"Phosphorescent","EmployeeUuid":"be6794ac-fa2c-49a5-8578-394bc70d0e60","StatsModel":{"Sales":{"TotalSales":0.0,"SpentOnSnacks":0.0,"SpentOnOffers":0.0,"SpentOnPackageDeals":0.0,"GuestSpentOnSnacks":0.0,"GuestSpentOnOffers":0.0,"GuestSpentOnPackageDeals":0.0,"PaidWithBalance":0.0,"SpentOnBookings":0.0},"Income":{"TotalIncome":0.0,"CashIncome":0.0,"CardIncome":0.0,"CashSales":0.0,"CardSales":0.0,"CashDeposits":0.0,"CardDeposits":0.0},"PrizesBought":0,"RefundsCount":0,"TotalRefunds":0.0,"Taxes":null,"NextResetTime":"0001-01-01T00:00:00"},"AdminModeCount":0,"ShiftsList":[]},{"Name":"tristamwarwick","EmployeeUuid":"bf6fb085-2623-4482-b6e2-96732d618b16","StatsModel":{"Sales":{"TotalSales":0.0,"SpentOnSnacks":0.0,"SpentOnOffers":0.0,"SpentOnPackageDeals":0.0,"GuestSpentOnSnacks":0.0,"GuestSpentOnOffers":0.0,"GuestSpentOnPackageDeals":0.0,"PaidWithBalance":0.0,"SpentOnBookings":0.0},"Income":{"TotalIncome":0.0,"CashIncome":0.0,"CardIncome":0.0,"CashSales":0.0,"CardSales":0.0,"CashDeposits":0.0,"CardDeposits":0.0},"PrizesBought":0,"RefundsCount":0,"TotalRefunds":0.0,"Taxes":null,"NextResetTime":"0001-01-01T00:00:00"},"AdminModeCount":0,"ShiftsList":[]},{"Name":"madlife","EmployeeUuid":"c0460d3c-4cbe-4a94-a5e5-4d40dcb25151","StatsModel":{"Sales":{"TotalSales":0.0,"SpentOnSnacks":0.0,"SpentOnOffers":0.0,"SpentOnPackageDeals":0.0,"GuestSpentOnSnacks":0.0,"GuestSpentOnOffers":0.0,"GuestSpentOnPackageDeals":0.0,"PaidWithBalance":0.0,"SpentOnBookings":0.0},"Income":{"TotalIncome":0.0,"CashIncome":0.0,"CardIncome":0.0,"CashSales":0.0,"CardSales":0.0,"CashDeposits":0.0,"CardDeposits":0.0},"PrizesBought":0,"RefundsCount":0,"TotalRefunds":0.0,"Taxes":null,"NextResetTime":"0001-01-01T00:00:00"},"AdminModeCount":0,"ShiftsList":[]},{"Name":"ChelseaHS","EmployeeUuid":"c444afec-c019-4102-9ca2-c9bcb52a114c","StatsModel":{"Sales":{"TotalSales":0.0,"SpentOnSnacks":0.0,"SpentOnOffers":0.0,"SpentOnPackageDeals":0.0,"GuestSpentOnSnacks":0.0,"GuestSpentOnOffers":0.0,"GuestSpentOnPackageDeals":0.0,"PaidWithBalance":0.0,"SpentOnBookings":0.0},"Income":{"TotalIncome":0.0,"CashIncome":0.0,"CardIncome":0.0,"CashSales":0.0,"CardSales":0.0,"CashDeposits":0.0,"CardDeposits":0.0},"PrizesBought":0,"RefundsCount":0,"TotalRefunds":0.0,"Taxes":null,"NextResetTime":"0001-01-01T00:00:00"},"AdminModeCount":0,"ShiftsList":[]},{"Name":"shadow","EmployeeUuid":"edd4366f-3a33-4522-98bf-fce726929206","StatsModel":{"Sales":{"TotalSales":0.0,"SpentOnSnacks":0.0,"SpentOnOffers":0.0,"SpentOnPackageDeals":0.0,"GuestSpentOnSnacks":0.0,"GuestSpentOnOffers":0.0,"GuestSpentOnPackageDeals":0.0,"PaidWithBalance":0.0,"SpentOnBookings":0.0},"Income":{"TotalIncome":0.0,"CashIncome":0.0,"CardIncome":0.0,"CashSales":0.0,"CardSales":0.0,"CashDeposits":0.0,"CardDeposits":0.0},"PrizesBought":0,"RefundsCount":0,"TotalRefunds":0.0,"Taxes":null,"NextResetTime":"0001-01-01T00:00:00"},"AdminModeCount":0,"ShiftsList":[]},{"Name":"SushiKebab17","EmployeeUuid":"edf1d8e5-b7cb-4467-a514-d7138f18e3dc","StatsModel":{"Sales":{"TotalSales":0.0,"SpentOnSnacks":0.0,"SpentOnOffers":0.0,"SpentOnPackageDeals":0.0,"GuestSpentOnSnacks":0.0,"GuestSpentOnOffers":0.0,"GuestSpentOnPackageDeals":0.0,"PaidWithBalance":0.0,"SpentOnBookings":0.0},"Income":{"TotalIncome":0.0,"CashIncome":0.0,"CardIncome":0.0,"CashSales":0.0,"CardSales":0.0,"CashDeposits":0.0,"CardDeposits":0.0},"PrizesBought":0,"RefundsCount":0,"TotalRefunds":0.0,"Taxes":null,"NextResetTime":"0001-01-01T00:00:00"},"AdminModeCount":0,"ShiftsList":[]},{"Name":"bepis","EmployeeUuid":"fbad710a-d412-41ab-8f36-d25ecb1f6101","StatsModel":{"Sales":{"TotalSales":15.0,"SpentOnSnacks":0.0,"SpentOnOffers":15.0,"SpentOnPackageDeals":0.0,"GuestSpentOnSnacks":0.0,"GuestSpentOnOffers":0.0,"GuestSpentOnPackageDeals":0.0,"PaidWithBalance":0.0,"SpentOnBookings":0.0},"Income":{"TotalIncome":15.0,"CashIncome":15.0,"CardIncome":0.0,"CashSales":15.0,"CardSales":0.0,"CashDeposits":0.0,"CardDeposits":0.0},"PrizesBought":0,"RefundsCount":0,"TotalRefunds":0.0,"Taxes":null,"NextResetTime":"0001-01-01T00:00:00"},"AdminModeCount":0,"ShiftsList":[]}],"Coins":0,"TimeSpent":"11:49:47","AvgTimeSpent":"01:28:43.3750000","Top":{"UsersByDeposits":[],"UsersByMoneySpent":[{"Uuid":"a0cf5c6d-299e-4a13-be8b-61d8613d5681","UserName":"ndroumev","TotalMoneySpent":15.0},{"Uuid":"6cf12df2-ebe1-4a39-9298-d48ac65443d7","UserName":"levs1","TotalMoneySpent":8.0},{"Uuid":"4fd34cc0-d4d6-43da-9613-a48fcb327928","UserName":"suetrev","TotalMoneySpent":5.0}],"Games":[{"Uuid":"5783f1f7-02a0-4ffe-8521-bd1e14f825b7","GameName":"Valorant","NumberOfPlays":27},{"Uuid":"0c20c601-2bd6-4e4d-92f5-e5511a0e7ba5","GameName":"League Of Legends","NumberOfPlays":2},{"Uuid":"8cb7caa3-f507-4fe7-ae0f-7322eb7f750b","GameName":"Counter Strike: Global Offensive","NumberOfPlays":1},{"Uuid":"acc33996-6af4-40dc-850c-e1f00bc86371","GameName":"Call Of Duty Warzone","NumberOfPlays":1}],"UsersByCoinsSpent":[]},"Taxes":[{"Id":"1","Name":"Tax 1","Percentage":0.0,"Square":null},{"Id":"2","Name":"Tax 2","Percentage":0.0,"Square":null},{"Id":"3","Name":"Tax 3","Percentage":0.0,"Square":null}]},"GuestSessionsReport":{"GuestSessionsStats":{"FreePlay":{"NumberOfSessions":19,"TotalTimePlayed":58744.0,"TotalPaid":0.0,"Activities":[{"Uuid":"44d49bdb-e164-47a4-ba03-1c09f63a21be","DateTime":"2022-02-14T22:43:57.43Z","Action":"LoggedOutGuest","CenterUuid":"7a4a5db0-2e79-41c0-a02d-5e82facd83c2","UserUuid":null,"EmployeeUuid":null,"MachineUuid":"5af2f268-d04c-412c-94e1-dd7c180d9c3d","DeviceUuid":null,"IsGuest":true,"Data":{"Duration":"00:00:12","SessionType":"FreePlay","MaxLength":"0","PaymentAmount":"0"}},{"Uuid":"09b69e21-cfe6-45e5-9adc-0a146786f085","DateTime":"2022-02-14T22:43:43.729Z","Action":"LoggedInGuest","CenterUuid":"7a4a5db0-2e79-41c0-a02d-5e82facd83c2","UserUuid":null,"EmployeeUuid":"1bafbd92-a05e-47a1-95f3-e9c70a945c59","MachineUuid":"5af2f268-d04c-412c-94e1-dd7c180d9c3d","DeviceUuid":null,"IsGuest":true,"Data":{"PaymentMethod":"Cash","SessionType":"FreePlay","MaxLength":"0","PaymentAmount":"0"}},{"Uuid":"219a92c9-0807-421c-a9cd-cfa3bce58a5c","DateTime":"2022-02-14T22:41:12.891Z","Action":"LoggedOutGuest","CenterUuid":"7a4a5db0-2e79-41c0-a02d-5e82facd83c2","UserUuid":null,"EmployeeUuid":null,"MachineUuid":"5af2f268-d04c-412c-94e1-dd7c180d9c3d","DeviceUuid":null,"IsGuest":true,"Data":{"Duration":"00:04:48","SessionType":"FreePlay","MaxLength":"0","PaymentAmount":"0"}},{"Uuid":"ecb53492-c0ca-4b2f-aff0-67217e23376f","DateTime":"2022-02-14T22:38:47.824Z","Action":"LoggedOutGuest","CenterUuid":"7a4a5db0-2e79-41c0-a02d-5e82facd83c2","UserUuid":null,"EmployeeUuid":null,"MachineUuid":"2c5d37f6-d80c-48b4-acf2-ff6bce5c5920","DeviceUuid":null,"IsGuest":true,"Data":{"Duration":"00:02:22","SessionType":"FreePlay","MaxLength":"0","PaymentAmount":"0"}},{"Uuid":"d212327d-b183-4837-80fd-de9f48e267a4","DateTime":"2022-02-14T22:36:24.245Z","Action":"LoggedInGuest","CenterUuid":"7a4a5db0-2e79-41c0-a02d-5e82facd83c2","UserUuid":null,"EmployeeUuid":"1bafbd92-a05e-47a1-95f3-e9c70a945c59","MachineUuid":"2c5d37f6-d80c-48b4-acf2-ff6bce5c5920","DeviceUuid":null,"IsGuest":true,"Data":{"PaymentMethod":"Cash","SessionType":"FreePlay","MaxLength":"0","PaymentAmount":"0"}},{"Uuid":"b8004e30-763a-4814-b229-02a6fbde080c","DateTime":"2022-02-14T22:36:24.038Z","Action":"LoggedInGuest","CenterUuid":"7a4a5db0-2e79-41c0-a02d-5e82facd83c2","UserUuid":null,"EmployeeUuid":"1bafbd92-a05e-47a1-95f3-e9c70a945c59","MachineUuid":"5af2f268-d04c-412c-94e1-dd7c180d9c3d","DeviceUuid":null,"IsGuest":true,"Data":{"PaymentMethod":"Cash","SessionType":"FreePlay","MaxLength":"0","PaymentAmount":"0"}},{"Uuid":"b266468d-1cb9-4a99-911f-cc4b9e9f4fb1","DateTime":"2022-02-14T22:32:28.26Z","Action":"LoggedOutGuest","CenterUuid":"7a4a5db0-2e79-41c0-a02d-5e82facd83c2","UserUuid":null,"EmployeeUuid":null,"MachineUuid":"0552990e-2715-45b1-a5fc-3426449b9a5a","DeviceUuid":null,"IsGuest":true,"Data":{"Duration":"00:00:12","SessionType":"FreePlay","MaxLength":"0","PaymentAmount":"0"}},{"Uuid":"47fc34e9-fd8d-45d3-b050-c310de3aa052","DateTime":"2022-02-14T22:32:15.314Z","Action":"LoggedInGuest","CenterUuid":"7a4a5db0-2e79-41c0-a02d-5e82facd83c2","UserUuid":null,"EmployeeUuid":"1bafbd92-a05e-47a1-95f3-e9c70a945c59","MachineUuid":"0552990e-2715-45b1-a5fc-3426449b9a5a","DeviceUuid":null,"IsGuest":true,"Data":{"PaymentMethod":"Cash","SessionType":"FreePlay","MaxLength":"0","PaymentAmount":"0"}},{"Uuid":"7227fc85-b3b9-4d2f-afbe-89cef3ec402e","DateTime":"2022-02-14T22:23:20.674Z","Action":"LoggedOutGuest","CenterUuid":"7a4a5db0-2e79-41c0-a02d-5e82facd83c2","UserUuid":null,"EmployeeUuid":null,"MachineUuid":"0fb9de70-e9bb-4c9d-b57b-87cbe633b444","DeviceUuid":null,"IsGuest":true,"Data":{"Duration":"00:00:25","SessionType":"FreePlay","MaxLength":"0","PaymentAmount":"0"}},{"Uuid":"de2f8994-d1e9-498d-85b4-8ba7b62fdd45","DateTime":"2022-02-14T22:22:54.693Z","Action":"LoggedInGuest","CenterUuid":"7a4a5db0-2e79-41c0-a02d-5e82facd83c2","UserUuid":null,"EmployeeUuid":"1bafbd92-a05e-47a1-95f3-e9c70a945c59","MachineUuid":"0fb9de70-e9bb-4c9d-b57b-87cbe633b444","DeviceUuid":null,"IsGuest":true,"Data":{"PaymentMethod":"Cash","SessionType":"FreePlay","MaxLength":"0","PaymentAmount":"0"}},{"Uuid":"6a3991eb-e1fa-4a67-a812-c967ef317b3e","DateTime":"2022-02-14T22:22:03.78Z","Action":"LoggedOutGuest","CenterUuid":"7a4a5db0-2e79-41c0-a02d-5e82facd83c2","UserUuid":null,"EmployeeUuid":null,"MachineUuid":"5d624947-937b-43e4-9e1d-e282b285b6a5","DeviceUuid":null,"IsGuest":true,"Data":{"Duration":"00:01:28","SessionType":"FreePlay","MaxLength":"0","PaymentAmount":"0"}},{"Uuid":"79060ce5-df86-46c3-a902-b4be87ba73c5","DateTime":"2022-02-14T22:21:55.869Z","Action":"LoggedOutGuest","CenterUuid":"7a4a5db0-2e79-41c0-a02d-5e82facd83c2","UserUuid":null,"EmployeeUuid":null,"MachineUuid":"60ef45ab-62b7-491f-8f02-9687c2d2ee64","DeviceUuid":null,"IsGuest":true,"Data":{"Duration":"00:01:20","SessionType":"FreePlay","MaxLength":"0","PaymentAmount":"0"}},{"Uuid":"65c6ff6f-1495-4c62-96e0-07d6434b15ca","DateTime":"2022-02-14T22:21:22.295Z","Action":"LoggedOutGuest","CenterUuid":"7a4a5db0-2e79-41c0-a02d-5e82facd83c2","UserUuid":null,"EmployeeUuid":null,"MachineUuid":"bfda2787-5a5c-415f-b27e-4242b5e3c301","DeviceUuid":null,"IsGuest":true,"Data":{"Duration":"00:00:46","SessionType":"FreePlay","MaxLength":"0","PaymentAmount":"0"}},{"Uuid":"5d8cc14c-8819-4deb-9be3-2e4633c39b4a","DateTime":"2022-02-14T22:21:14.244Z","Action":"LoggedOutGuest","CenterUuid":"7a4a5db0-2e79-41c0-a02d-5e82facd83c2","UserUuid":null,"EmployeeUuid":null,"MachineUuid":"5b566105-6047-4e92-853c-dc7804e8f66e","DeviceUuid":null,"IsGuest":true,"Data":{"Duration":"00:00:38","SessionType":"FreePlay","MaxLength":"0","PaymentAmount":"0"}},{"Uuid":"94a5dd8e-aa58-429e-bc8a-b9ce545b00e0","DateTime":"2022-02-14T22:21:00.31Z","Action":"LoggedOutGuest","CenterUuid":"7a4a5db0-2e79-41c0-a02d-5e82facd83c2","UserUuid":null,"EmployeeUuid":null,"MachineUuid":"2e07714e-2f08-4317-b6ce-0814198e03f0","DeviceUuid":null,"IsGuest":true,"Data":{"Duration":"00:00:24","SessionType":"FreePlay","MaxLength":"0","PaymentAmount":"0"}},{"Uuid":"62f86b5f-31db-4c1f-8998-2019984c6b62","DateTime":"2022-02-14T22:20:49.296Z","Action":"LoggedOutGuest","CenterUuid":"7a4a5db0-2e79-41c0-a02d-5e82facd83c2","UserUuid":null,"EmployeeUuid":null,"MachineUuid":"00904470-dc2a-4d6b-8aae-5b5946e0dd93","DeviceUuid":null,"IsGuest":true,"Data":{"Duration":"00:00:14","SessionType":"FreePlay","MaxLength":"0","PaymentAmount":"0"}},{"Uuid":"0181dbe2-f71b-4e40-b4ca-e86fd7efb3db","DateTime":"2022-02-14T22:20:34.982Z","Action":"LoggedInGuest","CenterUuid":"7a4a5db0-2e79-41c0-a02d-5e82facd83c2","UserUuid":null,"EmployeeUuid":"1bafbd92-a05e-47a1-95f3-e9c70a945c59","MachineUuid":"bfda2787-5a5c-415f-b27e-4242b5e3c301","DeviceUuid":null,"IsGuest":true,"Data":{"PaymentMethod":"Cash","SessionType":"FreePlay","MaxLength":"0","PaymentAmount":"0"}},{"Uuid":"b41f65cf-265f-406e-8e78-b9c72676e633","DateTime":"2022-02-14T22:20:34.97Z","Action":"LoggedInGuest","CenterUuid":"7a4a5db0-2e79-41c0-a02d-5e82facd83c2","UserUuid":null,"EmployeeUuid":"1bafbd92-a05e-47a1-95f3-e9c70a945c59","MachineUuid":"00904470-dc2a-4d6b-8aae-5b5946e0dd93","DeviceUuid":null,"IsGuest":true,"Data":{"PaymentMethod":"Cash","SessionType":"FreePlay","MaxLength":"0","PaymentAmount":"0"}},{"Uuid":"6d07db29-bdd8-4f07-a46e-c6ade41969f5","DateTime":"2022-02-14T22:20:34.737Z","Action":"LoggedInGuest","CenterUuid":"7a4a5db0-2e79-41c0-a02d-5e82facd83c2","UserUuid":null,"EmployeeUuid":"1bafbd92-a05e-47a1-95f3-e9c70a945c59","MachineUuid":"2e07714e-2f08-4317-b6ce-0814198e03f0","DeviceUuid":null,"IsGuest":true,"Data":{"PaymentMethod":"Cash","SessionType":"FreePlay","MaxLength":"0","PaymentAmount":"0"}},{"Uuid":"7ab22a82-b727-4cb2-9742-8f9cfeeaafe4","DateTime":"2022-02-14T22:20:34.577Z","Action":"LoggedInGuest","CenterUuid":"7a4a5db0-2e79-41c0-a02d-5e82facd83c2","UserUuid":null,"EmployeeUuid":"1bafbd92-a05e-47a1-95f3-e9c70a945c59","MachineUuid":"5b566105-6047-4e92-853c-dc7804e8f66e","DeviceUuid":null,"IsGuest":true,"Data":{"PaymentMethod":"Cash","SessionType":"FreePlay","MaxLength":"0","PaymentAmount":"0"}},{"Uuid":"b172deb4-68c1-44f7-8391-0d1601b38bf8","DateTime":"2022-02-14T22:20:34.424Z","Action":"LoggedInGuest","CenterUuid":"7a4a5db0-2e79-41c0-a02d-5e82facd83c2","UserUuid":null,"EmployeeUuid":"1bafbd92-a05e-47a1-95f3-e9c70a945c59","MachineUuid":"60ef45ab-62b7-491f-8f02-9687c2d2ee64","DeviceUuid":null,"IsGuest":true,"Data":{"PaymentMethod":"Cash","SessionType":"FreePlay","MaxLength":"0","PaymentAmount":"0"}},{"Uuid":"0f8b008e-30cb-4e3f-a199-f1f2bdca1d37","DateTime":"2022-02-14T22:20:34.423Z","Action":"LoggedInGuest","CenterUuid":"7a4a5db0-2e79-41c0-a02d-5e82facd83c2","UserUuid":null,"EmployeeUuid":"1bafbd92-a05e-47a1-95f3-e9c70a945c59","MachineUuid":"5d624947-937b-43e4-9e1d-e282b285b6a5","DeviceUuid":null,"IsGuest":true,"Data":{"PaymentMethod":"Cash","SessionType":"FreePlay","MaxLength":"0","PaymentAmount":"0"}},{"Uuid":"6bd4f1e5-5f3a-47ed-bf1d-916974ddbe28","DateTime":"2022-02-14T22:17:53.265Z","Action":"LoggedOutGuest","CenterUuid":"7a4a5db0-2e79-41c0-a02d-5e82facd83c2","UserUuid":null,"EmployeeUuid":null,"MachineUuid":"da5d282c-d4ce-419c-a9e8-0b716cc708d1","DeviceUuid":null,"IsGuest":true,"Data":{"Duration":"00:01:02","SessionType":"FreePlay","MaxLength":"0","PaymentAmount":"0"}},{"Uuid":"1fc760c8-fe32-42b9-a2ad-a443cec28a8c","DateTime":"2022-02-14T22:17:24.681Z","Action":"LoggedOutGuest","CenterUuid":"7a4a5db0-2e79-41c0-a02d-5e82facd83c2","UserUuid":null,"EmployeeUuid":null,"MachineUuid":"89aa9572-132c-4502-84aa-75058f715cff","DeviceUuid":null,"IsGuest":true,"Data":{"Duration":"00:00:29","SessionType":"FreePlay","MaxLength":"0","PaymentAmount":"0"}},{"Uuid":"ed63ee40-7f1f-4205-be55-e6a03e6bbc6a","DateTime":"2022-02-14T22:16:55.118Z","Action":"LoggedInGuest","CenterUuid":"7a4a5db0-2e79-41c0-a02d-5e82facd83c2","UserUuid":null,"EmployeeUuid":"1bafbd92-a05e-47a1-95f3-e9c70a945c59","MachineUuid":"89aa9572-132c-4502-84aa-75058f715cff","DeviceUuid":null,"IsGuest":true,"Data":{"PaymentMethod":"Cash","SessionType":"FreePlay","MaxLength":"0","PaymentAmount":"0"}},{"Uuid":"b5b3482e-aaa6-4e83-a395-cc1a3922cc6f","DateTime":"2022-02-14T22:16:50.53Z","Action":"LoggedInGuest","CenterUuid":"7a4a5db0-2e79-41c0-a02d-5e82facd83c2","UserUuid":null,"EmployeeUuid":"1bafbd92-a05e-47a1-95f3-e9c70a945c59","MachineUuid":"da5d282c-d4ce-419c-a9e8-0b716cc708d1","DeviceUuid":null,"IsGuest":true,"Data":{"PaymentMethod":"Cash","SessionType":"FreePlay","MaxLength":"0","PaymentAmount":"0"}},{"Uuid":"9b5b97fb-b196-4100-b7dc-7a1c394ba6f4","DateTime":"2022-02-14T22:15:40.286Z","Action":"LoggedOutGuest","CenterUuid":"7a4a5db0-2e79-41c0-a02d-5e82facd83c2","UserUuid":null,"EmployeeUuid":null,"MachineUuid":"8c2bf2b8-175d-4eb0-9613-b3f00f6c780f","DeviceUuid":null,"IsGuest":true,"Data":{"Duration":"00:00:07","SessionType":"FreePlay","MaxLength":"0","PaymentAmount":"0"}},{"Uuid":"20874559-69fa-4161-b05c-7296f3ce73ad","DateTime":"2022-02-14T22:15:32.155Z","Action":"LoggedInGuest","CenterUuid":"7a4a5db0-2e79-41c0-a02d-5e82facd83c2","UserUuid":null,"EmployeeUuid":"1bafbd92-a05e-47a1-95f3-e9c70a945c59","MachineUuid":"8c2bf2b8-175d-4eb0-9613-b3f00f6c780f","DeviceUuid":null,"IsGuest":true,"Data":{"PaymentMethod":"Cash","SessionType":"FreePlay","MaxLength":"0","PaymentAmount":"0"}},{"Uuid":"c0a72de8-efe5-4840-9c03-87cb5b091001","DateTime":"2022-02-14T22:14:51.037Z","Action":"LoggedOutGuest","CenterUuid":"7a4a5db0-2e79-41c0-a02d-5e82facd83c2","UserUuid":null,"EmployeeUuid":null,"MachineUuid":"b8f8bded-8a38-4e6a-b912-f863a3a06be4","DeviceUuid":null,"IsGuest":true,"Data":{"Duration":"03:12:50","SessionType":"FreePlay","MaxLength":"0","PaymentAmount":"0","SessionName":"NSE VALORANT"}},{"Uuid":"ae7abe3d-efea-4e22-ad4e-2048c31067f9","DateTime":"2022-02-14T22:14:39.301Z","Action":"LoggedOutGuest","CenterUuid":"7a4a5db0-2e79-41c0-a02d-5e82facd83c2","UserUuid":null,"EmployeeUuid":null,"MachineUuid":"4f9e537e-169b-41d5-a764-00eeadc0dfb6","DeviceUuid":null,"IsGuest":true,"Data":{"Duration":"03:12:38","SessionType":"FreePlay","MaxLength":"0","PaymentAmount":"0","SessionName":"NSE VALORANT"}},{"Uuid":"c81265f8-e15e-427e-bd97-f699a5297029","DateTime":"2022-02-14T22:14:26.489Z","Action":"LoggedOutGuest","CenterUuid":"7a4a5db0-2e79-41c0-a02d-5e82facd83c2","UserUuid":null,"EmployeeUuid":null,"MachineUuid":"de4c7569-489c-444f-a0de-e8c18025510b","DeviceUuid":null,"IsGuest":true,"Data":{"Duration":"03:12:57","SessionType":"FreePlay","MaxLength":"0","PaymentAmount":"0","SessionName":"NSE VALORANT"}},{"Uuid":"45990f83-e454-42d3-ad89-44f0b11ecd78","DateTime":"2022-02-14T22:13:24.516Z","Action":"LoggedOutGuest","CenterUuid":"7a4a5db0-2e79-41c0-a02d-5e82facd83c2","UserUuid":null,"EmployeeUuid":null,"MachineUuid":"5bbc2843-f303-488d-b34f-80e198f43e78","DeviceUuid":null,"IsGuest":true,"Data":{"Duration":"03:14:28","SessionType":"FreePlay","MaxLength":"0","PaymentAmount":"0","SessionName":"NSE VALORANT"}},{"Uuid":"4597fc19-bf3e-471c-ac45-60a9c904d0ea","DateTime":"2022-02-14T22:13:02.038Z","Action":"LoggedOutGuest","CenterUuid":"7a4a5db0-2e79-41c0-a02d-5e82facd83c2","UserUuid":null,"EmployeeUuid":null,"MachineUuid":"82fc65b4-e6da-48e7-b33c-294d63ffe662","DeviceUuid":null,"IsGuest":true,"Data":{"Duration":"03:11:44","SessionType":"FreePlay","MaxLength":"0","PaymentAmount":"0","SessionName":"NSE VALORANT"}},{"Uuid":"0eb8dc8a-c1a0-47bd-b143-07511338f5f4","DateTime":"2022-02-14T19:01:50.743Z","Action":"LoggedInGuest","CenterUuid":"7a4a5db0-2e79-41c0-a02d-5e82facd83c2","UserUuid":null,"EmployeeUuid":"fbad710a-d412-41ab-8f36-d25ecb1f6101","MachineUuid":"4f9e537e-169b-41d5-a764-00eeadc0dfb6","DeviceUuid":null,"IsGuest":true,"Data":{"PaymentMethod":"Cash","SessionType":"FreePlay","MaxLength":"0","PaymentAmount":"0","SessionName":"NSE VALORANT"}},{"Uuid":"d1ab7118-180c-45f6-bfe1-9c8184017b0b","DateTime":"2022-02-14T19:01:50.505Z","Action":"LoggedInGuest","CenterUuid":"7a4a5db0-2e79-41c0-a02d-5e82facd83c2","UserUuid":null,"EmployeeUuid":"fbad710a-d412-41ab-8f36-d25ecb1f6101","MachineUuid":"b8f8bded-8a38-4e6a-b912-f863a3a06be4","DeviceUuid":null,"IsGuest":true,"Data":{"PaymentMethod":"Cash","SessionType":"FreePlay","MaxLength":"0","PaymentAmount":"0","SessionName":"NSE VALORANT"}},{"Uuid":"2c68e352-e364-4f2f-9473-3037e031adb0","DateTime":"2022-02-14T19:01:08.477Z","Action":"LoggedInGuest","CenterUuid":"7a4a5db0-2e79-41c0-a02d-5e82facd83c2","UserUuid":null,"EmployeeUuid":"fbad710a-d412-41ab-8f36-d25ecb1f6101","MachineUuid":"82fc65b4-e6da-48e7-b33c-294d63ffe662","DeviceUuid":null,"IsGuest":true,"Data":{"PaymentMethod":"Cash","SessionType":"FreePlay","MaxLength":"0","PaymentAmount":"0","SessionName":"NSE VALORANT"}},{"Uuid":"8c468365-4a40-4e1f-89f3-da12a51663bd","DateTime":"2022-02-14T19:01:08.408Z","Action":"LoggedInGuest","CenterUuid":"7a4a5db0-2e79-41c0-a02d-5e82facd83c2","UserUuid":null,"EmployeeUuid":"fbad710a-d412-41ab-8f36-d25ecb1f6101","MachineUuid":"de4c7569-489c-444f-a0de-e8c18025510b","DeviceUuid":null,"IsGuest":true,"Data":{"PaymentMethod":"Cash","SessionType":"FreePlay","MaxLength":"0","PaymentAmount":"0","SessionName":"NSE VALORANT"}},{"Uuid":"e8a5c33b-8664-43fb-81a5-5e7452269302","DateTime":"2022-02-14T18:58:42.732Z","Action":"LoggedInGuest","CenterUuid":"7a4a5db0-2e79-41c0-a02d-5e82facd83c2","UserUuid":null,"EmployeeUuid":"fbad710a-d412-41ab-8f36-d25ecb1f6101","MachineUuid":"5bbc2843-f303-488d-b34f-80e198f43e78","DeviceUuid":null,"IsGuest":true,"Data":{"PaymentMethod":"Cash","SessionType":"FreePlay","MaxLength":"0","PaymentAmount":"0","SessionName":"NSE VALORANT"}}]}}},"EmployeeUuid":null,"ShiftUuid":null,"Start":"2022-02-14T10:00:00Z","End":"2022-02-14T23:59:00Z"}